adaptdl_sched/__init__.py
adaptdl_sched/__main__.py
adaptdl_sched/allocator.py
adaptdl_sched/cluster_expander.py
adaptdl_sched/config.py
adaptdl_sched/controller.py
adaptdl_sched/k8s_templates.py
adaptdl_sched/resources.py
adaptdl_sched/resources_test.py
adaptdl_sched/supervisor.py
adaptdl_sched/utils.py
adaptdl_sched/validator.py
adaptdl_sched/validator_test.py
adaptdl_sched/policy/__init__.py
adaptdl_sched/policy/non_preemptible_test.py
adaptdl_sched/policy/pollux.py
adaptdl_sched/policy/pollux_test.py
adaptdl_sched/policy/speedup.py
adaptdl_sched/policy/speedup_test.py
adaptdl_sched/policy/utils.py
adaptdl_sched-0.2.11.dist-info/METADATA
adaptdl_sched-0.2.11.dist-info/WHEEL
adaptdl_sched-0.2.11.dist-info/top_level.txt
adaptdl_sched-0.2.11.dist-info/RECORD
